test/code-quatus/I2C_RX_modelsim/I2C_RX.v
 

module I2C_RX(
    input clk,
    input rst,
    input enable,
    input [7:0] add,

    output reg [15:0] data,
    output reg done,
    inout scl_i2c,
    inout sda
);

    parameter START_W = -1;
    parameter SEND_ADDRESS = 0;
    parameter READ_ACK = 1;
    parameter IDLE = 2;
    parameter SEND_DATA = 3, READ_DATA = 3;
    parameter READ_ACK_NACK = 4, SEND_ACK_NACK = 4;
    parameter PRE_STOP = 5;
    parameter STOP = 6;
   
    integer state = 0;
    integer count = 7;
    integer count_byte = 0;
    integer enddelay = 4;
    integer ck = 3;
    
    integer pause = 0;

    reg temp = 1;
    reg checkACK = 0;
    reg checkBug = 0;
    reg scl;
    
    assign scl_i2c = (enable)?scl:1'bz;
    assign sda = (~enable || state == IDLE || state == SEND_DATA)?1'bz:temp;
    
    always @(posedge clk) begin
        if (~rst | ~enable) begin
            ck <= 3; pause <= 0; count <= 7; count_byte = 0;					                                   
            state <= 0;
            scl <= 1;						                                   
            done <= 0;
        end
        else begin
            done <= 0;
            scl <= 1;						                                                        
            if (enable) begin
                if (pause == 0) begin							                                    
                    ck <= (ck != 3)?(ck + 1):0;
                    if ((ck == 0 | ck == 2)) scl <= ~scl;
                    else scl <= scl;

                    if(ck == 3 && (state == READ_ACK | state == READ_ACK_NACK)) checkACK <= sda;	
                    else checkACK <= 1'bZ;

                    if (state == SEND_ADDRESS && ck == 3 && count == 7) temp <= 0;		           
                    //else temp <= temp;

                    if (state == SEND_DATA && ck == 0 && count == 7) scl <= scl;
                    else if (state == STOP) scl <= 1;                                              				                
                end
                else begin
                    pause <= pause - 1;
                    if (state == SEND_DATA) scl <= 0;					                            
                    else if (state == STOP) ck <= 2;					                        
                    else ck <= ck;
                end


                if (((ck == 1 && (state <= IDLE||state >= READ_ACK_NACK))||(ck == 3 && state > IDLE && state < READ_ACK_NACK))&& pause == 0) begin
                    case (state) 
                        SEND_ADDRESS: begin						                                    
                            temp <= add[count];                
                            if (count != 0) count <= count - 1;
                            else begin
                                state <= READ_ACK;
                                count <= 7;		
                            end
                        end
                        READ_ACK: begin						                    
                            temp <= 1'bZ;					                    
                            if (1) state <= IDLE;
                            else begin
                                state <= SEND_ADDRESS;  
                                ck <= 0; 
                            end
                        end
                        IDLE: begin						                       
                            pause <= 4;
                            state <= SEND_DATA;
                            scl <= 0;					                        
                            temp <= 1'bz;
                            ck <= 0;
                        end
                        READ_DATA: begin						             
                            temp <= 1'bz;
                            data[count + 8 - count_byte*8] <= sda;
                            if (count != 0) count <= count - 1;
                            else begin
                                state <= READ_ACK_NACK;
                                count <= 7;
                                count_byte <= count_byte + 1;
                            end
                        end
                        READ_ACK_NACK: begin						          
                            if (count_byte == 2) begin
                                temp <= 1'b1;
                                count_byte <= 0;
                                state <= PRE_STOP;
                            end
                            else begin
                                if (~checkBug) begin
                                    temp <= 1'b0;
                                    checkBug <= 1'b1;
                                end 
                                else begin
                                    state <= SEND_DATA;
                                    temp <= 1'bz;
                                    checkBug <= 0;
                                end
                            end
                        end
                        PRE_STOP: begin						               
                            temp <= 0;
                            state <= STOP;
                        end
                        STOP: begin						                      
                            pause <= 60;                                    
                            temp <= 1'bz; scl <= 1; ck <= 3;  
                            done <= 1;
                            state <= SEND_ADDRESS;		
                        end
                    endcase
                end
            end
            else begin
                ck <= 3; pause <= 0; count <= 7; count_byte = 0;
                state <= SEND_ADDRESS;
                done <= 0;
            end
        end
    end
endmodule

test/code-quatus/I2C_RX_modelsim/tb_I2C_RX.v
`timescale 1ns / 1ps

module tb_I2C_RX;

    reg clk;
    reg rst;
    reg enable;
    reg [7:0] add;

    wire [15:0] data;
    wire done;
    wire scl_i2c;
    wire sda;

    reg sda_in;
    reg scl_in;
    wire sda_wire;
    wire scl_wire;

    // Pull up for inout lines
    assign sda_wire = sda_in ? 1'bz : 0;
    assign scl_wire = scl_in ? 1'bz : 0;

    assign sda = sda_wire;
    assign scl_i2c = scl_wire;

    I2C_RX uut (
        .clk(clk),
        .rst(rst),
        .enable(enable),
        .add(add),
        .data(data),
        .done(done),
        .scl_i2c(scl_wire),
        .sda(sda_wire)
    );

    // Clock generation
    initial begin
        clk = 0;
        forever #5 clk = ~clk; // 100MHz clock
    end

    initial begin
        // Init values
        rst = 0;
        enable = 0;
        add = 8'hA1; // Example address

        sda_in = 1;
        scl_in = 1;

        // Reset
        #20;
        rst = 1;

        #10;
        enable = 1;

        // Simulate some slave behavior for ACK
        // Simple emulation - for a real test, you would simulate actual I2C slave responses
        // Start sending ACKs or DATA after few cycles
        #200;
        sda_in = 0; // Simulate ACK from slave

        #100;
        sda_in = 1; // Release SDA

        // Let it run for a while
        #1000;

        // Stop simulation
        $finish;
    end

    initial begin
        $dumpfile("i2c_rx_tb.vcd");
        $dumpvars(0, tb_I2C_RX);
    end
	 
	 
	 // ... [giữ nguyên phần đầu testbench như trước]

    reg [15:0] fake_data = 16'hABCD;
    integer bit_index = 15;
    reg sending_data = 0;

    always @(negedge uut.scl_i2c) begin
        // Mô phỏng gửi dữ liệu từ slave khi ở trạng thái READ_DATA
        if (uut.state == uut.READ_DATA && sending_data == 1) begin
            sda_in = fake_data[bit_index];
            bit_index = bit_index - 1;
        end

        // Chuẩn bị gửi data khi vào READ_DATA
        if (uut.state == uut.READ_DATA && sending_data == 0) begin
            sending_data = 1;
            bit_index = 15;
        end

        // Sau khi gửi hết 16 bit
        if (bit_index < 0) begin
            sda_in = 1; // nhả SDA
            sending_data = 0;
        end
    end

    // ACK sau mỗi byte
    always @(posedge uut.scl_i2c) begin
        if (uut.state == uut.READ_ACK_NACK) begin
            sda_in = 0; // Giả lập ACK
        end
    end


endmodule

test/code-quatus/I2C_RX_modelsim/simulation/modelsim/i2c_rx_tb.vcd
$date
	Tue Apr 08 00:38:38 2025
$end
$version
	ModelSim Version 10.5b
$end
$timescale
	1ps
$end

$scope module tb_I2C_RX $end
$var reg 1 ! clk $end
$var reg 1 " rst $end
$var reg 1 # enable $end
$var reg 8 $ add [7:0] $end
$var wire 1 % data [15] $end
$var wire 1 & data [14] $end
$var wire 1 ' data [13] $end
$var wire 1 ( data [12] $end
$var wire 1 ) data [11] $end
$var wire 1 * data [10] $end
$var wire 1 + data [9] $end
$var wire 1 , data [8] $end
$var wire 1 - data [7] $end
$var wire 1 . data [6] $end
$var wire 1 / data [5] $end
$var wire 1 0 data [4] $end
$var wire 1 1 data [3] $end
$var wire 1 2 data [2] $end
$var wire 1 3 data [1] $end
$var wire 1 4 data [0] $end
$var wire 1 5 done $end
$var wire 1 6 scl_i2c $end
$var wire 1 7 sda $end
$var reg 1 8 sda_in $end
$var reg 1 9 scl_in $end
$var wire 1 : sda_wire $end
$var wire 1 ; scl_wire $end
$var reg 16 < fake_data [15:0] $end
$var integer 32 = bit_index $end
$var reg 1 > sending_data $end

$scope module uut $end
$var parameter 32 ? START_W $end
$var parameter 32 @ SEND_ADDRESS $end
$var parameter 32 A READ_ACK $end
$var parameter 32 B IDLE $end
$var parameter 32 C SEND_DATA $end
$var parameter 32 D READ_DATA $end
$var parameter 32 E READ_ACK_NACK $end
$var parameter 32 F SEND_ACK_NACK $end
$var parameter 32 G PRE_STOP $end
$var parameter 32 H STOP $end
$var wire 1 I clk $end
$var wire 1 J rst $end
$var wire 1 K enable $end
$var wire 1 L add [7] $end
$var wire 1 M add [6] $end
$var wire 1 N add [5] $end
$var wire 1 O add [4] $end
$var wire 1 P add [3] $end
$var wire 1 Q add [2] $end
$var wire 1 R add [1] $end
$var wire 1 S add [0] $end
$var reg 16 T data [15:0] $end
$var reg 1 U done $end
$var wire 1 ; scl_i2c $end
$var wire 1 : sda $end
$var integer 32 V state $end
$var integer 32 W count $end
$var integer 32 X count_byte $end
$var integer 32 Y enddelay $end
$var integer 32 Z ck $end
$var integer 32 [ pause $end
$var reg 1 \ temp $end
$var reg 1 ] checkACK $end
$var reg 1 ^ checkBug $end
$var reg 1 _ scl $end
$upscope $end
$upscope $end
$enddefinitions $end
#0
$dumpvars
0!
0"
0#
b10100001 $
18
19
bx T
xU
1\
0]
0^
x_
b1010101111001101 <
0>
b11111111111111111111111111111111 ?
b0 @
b1 A
b10 B
b11 C
b11 D
b100 E
b100 F
b101 G
b110 H
b0 V
b111 W
b0 X
b100 Y
b11 Z
b0 [
b1111 =
x4
x3
x2
x1
x0
x/
x.
x-
x,
x+
x*
x)
x(
x'
x&
x%
x5
z6
z7
z:
z;
1S
0R
0Q
0P
0O
1N
0M
1L
0K
0J
0I
$end
#5000
1!
1I
1_
0U
05
#10000
0!
0I
#15000
1!
1I
#20000
1"
0!
1J
0I
#25000
1!
1I
#30000
1#
0!
1K
1;
16
1:
17
0I
#35000
1!
1I
b0 Z
z]
0\
0:
07
#40000
0!
0I
#45000
1!
1I
b1 Z
0_
0;
06
#50000
0!
0I
#55000
1!
1I
1_
b10 Z
0_
1\
b110 W
1:
17
#60000
0!
0I
#65000
1!
1I
1_
b11 Z
1;
16
#70000
0!
0I
#75000
1!
1I
b0 Z
#80000
0!
0I
#85000
1!
1I
b1 Z
0_
0;
06
#90000
0!
0I
#95000
1!
1I
1_
b10 Z
0_
0\
b101 W
0:
07
#100000
0!
0I
#105000
1!
1I
1_
b11 Z
1;
16
#110000
0!
0I
#115000
1!
1I
b0 Z
#120000
0!
0I
#125000
1!
1I
b1 Z
0_
0;
06
#130000
0!
0I
#135000
1!
1I
1_
b10 Z
0_
1\
b100 W
1:
17
#140000
0!
0I
#145000
1!
1I
1_
b11 Z
1;
16
#150000
0!
0I
#155000
1!
1I
b0 Z
#160000
0!
0I
#165000
1!
1I
b1 Z
0_
0;
06
#170000
0!
0I
#175000
1!
1I
1_
b10 Z
0_
0\
b11 W
0:
07
#180000
0!
0I
#185000
1!
1I
1_
b11 Z
1;
16
#190000
0!
0I
#195000
1!
1I
b0 Z
#200000
0!
0I
#205000
1!
1I
b1 Z
0_
0;
06
#210000
0!
0I
#215000
1!
1I
1_
b10 Z
0_
b10 W
#220000
0!
0I
#225000
1!
1I
1_
b11 Z
1;
16
#230000
08
0!
0I
#235000
1!
1I
b0 Z
#240000
0!
0I
#245000
1!
1I
b1 Z
0_
0;
06
#250000
0!
0I
#255000
1!
1I
1_
b10 Z
0_
b1 W
#260000
0!
0I
#265000
1!
1I
1_
b11 Z
1;
16
#270000
0!
0I
#275000
1!
1I
b0 Z
#280000
0!
0I
#285000
1!
1I
b1 Z
0_
0;
06
#290000
0!
0I
#295000
1!
1I
1_
b10 Z
0_
b0 W
#300000
0!
0I
#305000
1!
1I
1_
b11 Z
1;
16
#310000
0!
0I
#315000
1!
1I
b0 Z
#320000
0!
0I
#325000
1!
1I
b1 Z
0_
0;
06
#330000
18
0!
0I
#335000
1!
1I
1_
b10 Z
0_
1\
b1 V
b111 W
1:
17
#340000
0!
0I
#345000
1!
1I
1_
b11 Z
1;
16
#350000
0!
0I
#355000
1!
1I
b0 Z
1]
#360000
0!
0I
#365000
1!
1I
b1 Z
0_
z]
0;
06
#370000
0!
0I
#375000
1!
1I
1_
b10 Z
0_
z\
b10 V
z:
z7
#380000
0!
0I
#385000
1!
1I
1_
b11 Z
1;
16
#390000
0!
0I
#395000
1!
1I
b0 Z
#400000
0!
0I
#405000
1!
1I
b1 Z
0_
0;
06
#410000
0!
0I
#415000
1!
1I
1_
b10 Z
0_
b100 [
b11 V
b0 Z
#420000
0!
0I
#425000
1!
1I
1_
b11 [
0_
#430000
0!
0I
#435000
1!
1I
1_
b10 [
0_
#440000
0!
0I
#445000
1!
1I
1_
b1 [
0_
#450000
0!
0I
#455000
1!
1I
1_
b0 [
0_
#460000
0!
0I
#465000
1!
1I
1_
b1 Z
0_
#470000
0!
0I
#475000
1!
1I
1_
b10 Z
0_
#480000
0!
0I
#485000
1!
1I
1_
b11 Z
1;
16
#490000
0!
0I
#495000
1!
1I
b0 Z
bzxxxxxxxxxxxxxxx T
b110 W
z%
#500000
0!
0I
#505000
1!
1I
b1 Z
0_
0;
06
1>
#510000
0!
0I
#515000
1!
1I
1_
b10 Z
0_
#520000
0!
0I
#525000
1!
1I
1_
b11 Z
1;
16
#530000
0!
0I
#535000
1!
1I
b0 Z
bzxxxxxxxxxxxxxx T
b101 W
z&
#540000
0!
0I
#545000
1!
1I
b1 Z
0_
0;
06
b1110 =
#550000
0!
0I
#555000
1!
1I
1_
b10 Z
0_
#560000
0!
0I
#565000
1!
1I
1_
b11 Z
1;
16
#570000
0!
0I
#575000
1!
1I
b0 Z
bzxxxxxxxxxxxxx T
b100 W
z'
#580000
0!
0I
#585000
1!
1I
b1 Z
0_
0;
06
08
b1101 =
0:
07
#590000
0!
0I
#595000
1!
1I
1_
b10 Z
0_
#600000
0!
0I
#605000
1!
1I
1_
b11 Z
1;
16
#610000
0!
0I
#615000
1!
1I
b0 Z
bz0xxxxxxxxxxxx T
b11 W
0(
#620000
0!
0I
#625000
1!
1I
b1 Z
0_
0;
06
18
b1100 =
z:
z7
#630000
0!
0I
#635000
1!
1I
1_
b10 Z
0_
#640000
0!
0I
#645000
1!
1I
1_
b11 Z
1;
16
#650000
0!
0I
#655000
1!
1I
b0 Z
bz0zxxxxxxxxxxx T
b10 W
z)
#660000
0!
0I
#665000
1!
1I
b1 Z
0_
0;
06
08
b1011 =
0:
07
#670000
0!
0I
#675000
1!
1I
1_
b10 Z
0_
#680000
0!
0I
#685000
1!
1I
1_
b11 Z
1;
16
#690000
0!
0I
#695000
1!
1I
b0 Z
bz0z0xxxxxxxxxx T
b1 W
0*
#700000
0!
0I
#705000
1!
1I
b1 Z
0_
0;
06
18
b1010 =
z:
z7
#710000
0!
0I
#715000
1!
1I
1_
b10 Z
0_
#720000
0!
0I
#725000
1!
1I
1_
b11 Z
1;
16
#730000
0!
0I
#735000
1!
1I
b0 Z
bz0z0zxxxxxxxxx T
b0 W
z+
#740000
0!
0I
#745000
1!
1I
b1 Z
0_
0;
06
08
b1001 =
0:
07
#750000
0!
0I
#755000
1!
1I
1_
b10 Z
0_
#760000
0!
0I
#765000
1!
1I
1_
b11 Z
1;
16
#770000
0!
0I
#775000
1!
1I
b0 Z
bz0z0z0xxxxxxxx T
b100 V
b111 W
b1 X
0,
#780000
0!
0I
#785000
1!
1I
b1 Z
0_
0;
06
#790000
0!
0I
#795000
1!
1I
1_
b10 Z
0_
0\
1^
#800000
0!
0I
#805000
1!
1I
1_
b11 Z
1;
16
#810000
0!
0I
#815000
1!
1I
b0 Z
0]
#820000
0!
0I
#825000
1!
1I
b1 Z
0_
z]
0;
06
#830000
0!
0I
#835000
1!
1I
1_
b10 Z
0_
b11 V
z\
0^
#840000
0!
0I
#845000
1!
1I
1_
b11 Z
1;
16
#850000
0!
0I
#855000
1!
1I
b0 Z
bz0z0z00xxxxxxx T
b110 W
0-
#860000
0!
0I
#865000
1!
1I
b1 Z
0_
0;
06
18
b1000 =
z:
z7
#870000
0!
0I
#875000
1!
1I
1_
b10 Z
0_
#880000
0!
0I
#885000
1!
1I
1_
b11 Z
1;
16
#890000
0!
0I
#895000
1!
1I
b0 Z
bz0z0z00zxxxxxx T
b101 W
z.
#900000
0!
0I
#905000
1!
1I
b1 Z
0_
0;
06
b111 =
#910000
0!
0I
#915000
1!
1I
1_
b10 Z
0_
#920000
0!
0I
#925000
1!
1I
1_
b11 Z
1;
16
#930000
0!
0I
#935000
1!
1I
b0 Z
bz0z0z00zzxxxxx T
b100 W
z/
#940000
0!
0I
#945000
1!
1I
b1 Z
0_
0;
06
b110 =
#950000
0!
0I
#955000
1!
1I
1_
b10 Z
0_
#960000
0!
0I
#965000
1!
1I
1_
b11 Z
1;
16
#970000
0!
0I
#975000
1!
1I
b0 Z
bz0z0z00zzzxxxx T
b11 W
z0
#980000
0!
0I
#985000
1!
1I
b1 Z
0_
0;
06
b101 =
#990000
0!
0I
#995000
1!
1I
1_
b10 Z
0_
#1000000
0!
0I
#1005000
1!
1I
1_
b11 Z
1;
16
#1010000
0!
0I
#1015000
1!
1I
b0 Z
bz0z0z00zzzzxxx T
b10 W
z1
#1020000
0!
0I
#1025000
1!
1I
b1 Z
0_
0;
06
08
b100 =
0:
07
#1030000
0!
0I
#1035000
1!
1I
1_
b10 Z
0_
#1040000
0!
0I
#1045000
1!
1I
1_
b11 Z
1;
16
#1050000
0!
0I
#1055000
1!
1I
b0 Z
bz0z0z00zzzz0xx T
b1 W
02
#1060000
0!
0I
#1065000
1!
1I
b1 Z
0_
0;
06
b11 =
#1070000
0!
0I
#1075000
1!
1I
1_
b10 Z
0_
#1080000
0!
0I
#1085000
1!
1I
1_
b11 Z
1;
16
#1090000
0!
0I
#1095000
1!
1I
b0 Z
bz0z0z00zzzz00x T
b0 W
03
#1100000
0!
0I
#1105000
1!
1I
b1 Z
0_
0;
06
18
b10 =
z:
z7
#1110000
0!
0I
#1115000
1!
1I
1_
b10 Z
0_
#1120000
0!
0I
#1125000
1!
1I
1_
b11 Z
1;
16
#1130000
0!
0I
#1135000
1!
1I
b0 Z
bz0z0z00zzzz00z T
b100 V
b111 W
b10 X
z4
#1140000
0!
0I
#1145000
1!
1I
b1 Z
0_
0;
06
#1150000
0!
0I
#1155000
1!
1I
1_
b10 Z
0_
1\
b0 X
b101 V
1:
17
#1160000
0!
0I
#1165000
1!
1I
1_
b11 Z
1;
16
#1170000
0!
0I
#1175000
1!
1I
b0 Z
#1180000
0!
0I
#1185000
1!
1I
b1 Z
0_
0;
06
#1190000
0!
0I
#1195000
1!
1I
1_
b10 Z
0_
0\
b110 V
0:
07
#1200000
0!
0I
#1205000
1!
1I
1_
b11 Z
1;
16
#1210000
0!
0I
#1215000
1!
1I
b0 Z
#1220000
0!
0I
#1225000
1!
1I
b1 Z
0_
1_
#1230000
0!
0I
#1235000
1!
1I
b10 Z
b111100 [
z\
b11 Z
1U
b0 V
z:
15
z7
#1240000
0!
0I
#1245000
1!
1I
0U
b111011 [
05
#1250000
0!
0I
#1255000
1!
1I
b111010 [
#1260000
0!
0I
#1265000
1!
1I
b111001 [
#1270000
0!
0I
#1275000
1!
1I
b111000 [
#1280000
0!
0I
#1285000
1!
1I
b110111 [
#1290000
0!
0I
#1295000
1!
1I
b110110 [
#1300000
0!
0I
#1305000
1!
1I
b110101 [
#1310000
0!
0I
#1315000
1!
1I
b110100 [
#1320000
0!
0I
#1325000
1!
1I
b110011 [
